LICENSE.md
MANIFEST.in
README.rst
pyproject.toml
requirements.core.txt
requirements.txt
setup.py
core_module_excel_uploader_app/__init__.py
core_module_excel_uploader_app/urls.py
core_module_excel_uploader_app.egg-info/PKG-INFO
core_module_excel_uploader_app.egg-info/SOURCES.txt
core_module_excel_uploader_app.egg-info/dependency_links.txt
core_module_excel_uploader_app.egg-info/requires.txt
core_module_excel_uploader_app.egg-info/top_level.txt
core_module_excel_uploader_app/static/core_module_excel_uploader_app/css/excel_uploader.css
core_module_excel_uploader_app/static/core_module_excel_uploader_app/js/excel_uploader.js
core_module_excel_uploader_app/static/core_module_excel_uploader_app/xls/data.xls
core_module_excel_uploader_app/templates/core_module_excel_uploader_app/excel_uploader.html
core_module_excel_uploader_app/views/__init__.py
core_module_excel_uploader_app/views/forms.py
core_module_excel_uploader_app/views/views.py
tests/__init__.py
tests/test_settings.py
tests/views/__init__.py
tests/views/views/__init__.py
tests/views/views/tests_unit.py