Metadata-Version: 2.1
Name: core-module-excel-uploader-app
Version: 2.19.0
Summary: Excel Uploader module for the parser core project
Home-page: https://github.com/usnistgov/core_module_excel_uploader_app
Author: NIST IT Lab
Author-email: itl_inquiries@nist.gov
License-File: LICENSE.md
